sdgrate/LibreBaskerville-DpdE.ttf
sdgrate/__init__.py
sdgrate/checkpoint_merger_mbw.py
sdgrate/grate.py
sdgrate-0.2.5.dist-info/LICENSE
sdgrate-0.2.5.dist-info/METADATA
sdgrate-0.2.5.dist-info/WHEEL
sdgrate-0.2.5.dist-info/entry_points.txt
sdgrate-0.2.5.dist-info/top_level.txt
sdgrate-0.2.5.dist-info/RECORD
