Metadata-Version: 2.1
Name: sdgrate
Version: 0.2.5
Summary: A grid image generator for Stable Diffusion models based on 🧨diffusers.
Author-email: Damian Stewart <null@damianstewart.com>
Project-URL: Homepage, https://github.com/damian0815/grate
Project-URL: Bug Tracker, https://github.com/damian0815/grate/issues
Classifier: Programming Language :: Python :: 3
Classifier: License :: OSI Approved :: GNU Affero General Public License v3
Classifier: Operating System :: OS Independent
Requires-Python: >=3.10
License-File: LICENSE
Requires-Dist: diffusers[torch] >=0.13
Requires-Dist: compel ~=1.1.3
Requires-Dist: huggingface-hub
Requires-Dist: Pillow
Requires-Dist: tqdm
Requires-Dist: transformers
Requires-Dist: scipy
